piec/__init__.py
piec/_version.py
piec/drivers/__init__.py
piec/drivers/instrument.py
piec/drivers/pymeasure_wrapper.py
piec/drivers/keysight81150a/__init__.py
piec/drivers/keysight81150a/core.py
piec/drivers/keysightdsox3024a/__init__.py
piec/drivers/keysightdsox3024a/core.py
piecs-0.0.1b3.dist-info/LICENSE
piecs-0.0.1b3.dist-info/METADATA
piecs-0.0.1b3.dist-info/WHEEL
piecs-0.0.1b3.dist-info/top_level.txt
piecs-0.0.1b3.dist-info/RECORD
