Metadata-Version: 2.1
Name: piecs
Version: 0.0.1b3
Summary: A collection of control and analysis code for experiments
Home-page: https://github.com/ElPsyKurisu/PIEC
Author: Geo Fratian
Author-email: geo_fratian@brown.edu
Project-URL: Bug Tracker, https://github.com/ElPsyKurisu/PIEC/issues
Project-URL: repository, https://github.com/ElPsyKurisu/PIEC
Classifier: Programming Language :: Python :: 3
Classifier: License :: OSI Approved :: MIT License
Classifier: Operating System :: OS Independent
Requires-Python: >=3.6
License-File: LICENSE
Requires-Dist: pandas>=1.3.2
Requires-Dist: numpy>=1.19.2
Requires-Dist: matplotlib>=3.3.4
Requires-Dist: scipy>=1.6.2
Requires-Dist: pyvisa>=1.11.3
Requires-Dist: IPython>=7.22.0
